AUTHORS
LICENSE.txt
MANIFEST.in
setup.py
django_jython.egg-info/PKG-INFO
django_jython.egg-info/SOURCES.txt
django_jython.egg-info/dependency_links.txt
django_jython.egg-info/not-zip-safe
django_jython.egg-info/requires.txt
django_jython.egg-info/top_level.txt
docs/Makefile
docs/conf.py
docs/database-backends.rst
docs/index.rst
docs/quickstart.rst
docs/release-notes.rst
docs/upload.sh
docs/war-deployment.rst
doj/__init__.py
doj/db/__init__.py
doj/db/backends/__init__.py
doj/db/backends/mssql/__init__.py
doj/db/backends/mssql/base.py
doj/db/backends/mssql/base_schema.py
doj/db/backends/mssql/compiler.py
doj/db/backends/mssql/creation.py
doj/db/backends/mssql/introspection.py
doj/db/backends/mssql/operations.py
doj/db/backends/mssql/schema.py
doj/db/backends/mysql/__init__.py
doj/db/backends/mysql/base.py
doj/db/backends/mysql/client.py
doj/db/backends/mysql/compiler.py
doj/db/backends/mysql/creation.py
doj/db/backends/mysql/introspection.py
doj/db/backends/mysql/schema.py
doj/db/backends/mysql/validation.py
doj/db/backends/postgresql/__init__.py
doj/db/backends/postgresql/base.py
doj/db/backends/postgresql/client.py
doj/db/backends/postgresql/compiler.py
doj/db/backends/postgresql/creation.py
doj/db/backends/postgresql/introspection.py
doj/db/backends/postgresql/operations.py
doj/db/backends/postgresql/schema.py
doj/db/backends/postgresql/version.py
doj/db/backends/sqlite/__init__.py
doj/db/backends/sqlite/base.py
doj/db/backends/sqlite/client.py
doj/db/backends/sqlite/creation.py
doj/db/backends/sqlite/introspection.py
doj/db/backends/sqlite/schema.py
doj/management/__init__.py
doj/management/commands/__init__.py
doj/management/commands/buildwar.py
doj/management/commands/jndiconfig.py
doj/management/commands/jndi_skel/jndidatasource.xml.tmpl
doj/management/commands/war_skel/wsgi.py.tmpl
doj/management/commands/war_skel/WEB-INF/web.xml.tmpl
doj/management/commands/war_skel/WEB-INF/lib/README
doj/management/commands/war_skel/WEB-INF/lib/jruby-extras-fileservlet.jar
doj/management/commands/war_skel/WEB-INF/lib-python/README
doj/management/commands/war_skel/WEB-INF/lib-python/application_settings.py.tmpl
doj/management/commands/war_skel/WEB-INF/lib-python/eggs.pth.tmpl
