Metadata-Version: 1.1
Name: django-jython
Version: 1.8.0b2
Summary: Database backends and management commands, for development under Django/Jython
Home-page: http://code.google.com/p/django-jython/
Author: Andreas Stocker
Author-email: andreas@st0cker.at
License: BSD
Keywords: django,jython,doj,database,java
Platform: UNKNOWN
Classifier: Development Status :: 4 - Beta
Classifier: Framework :: Django
Classifier: Intended Audience :: Developers
Classifier: License :: OSI Approved :: BSD License
Classifier: Programming Language :: Python
Classifier: Programming Language :: Java
Classifier: Programming Language :: Python :: Implementation :: Jython
